LICENSE
MANIFEST.in
README.rst
setup.cfg
setup.py
django_singleton_model.egg-info/PKG-INFO
django_singleton_model.egg-info/SOURCES.txt
django_singleton_model.egg-info/dependency_links.txt
django_singleton_model.egg-info/not-zip-safe
django_singleton_model.egg-info/requires.txt
django_singleton_model.egg-info/top_level.txt
singleton_model/__init__.py
singleton_model/models.py