Metadata-Version: 1.1
Name: django-singleton-model
Version: 0.2.1
Summary: Simple package for impleting models using singleton design pattern
Home-page: https://github.com/icaropires/django-singleton-model
Author: Ícaro Pires
Author-email: icaropsa@gmail.com
License: MIT
Platform: UNKNOWN
Classifier: Environment :: Web Environment
Classifier: Framework :: Django
Classifier: Framework :: Django :: 2.0
Classifier: Operating System :: OS Independent
Classifier: Programming Language :: Python :: 3
Classifier: Programming Language :: Python :: 3.5
Classifier: Programming Language :: Python :: 3.6
